cv_stream/__init__.py
cv_stream/camera.py
cv_stream/camera_server.py
cv_stream/templates/index.html
cv_stream-0.1.2.dist-info/LICENSE
cv_stream-0.1.2.dist-info/METADATA
cv_stream-0.1.2.dist-info/WHEEL
cv_stream-0.1.2.dist-info/top_level.txt
cv_stream-0.1.2.dist-info/RECORD
