Metadata-Version: 2.1
Name: cv-stream
Version: 0.1.2
Summary: Remote OpenCV development server
Home-page: https://github.com/bherbruck/cv_stream
Author: Brennen Herbruck
Author-email: brennen.hrbruck@gmail.com
License: UNKNOWN
Platform: UNKNOWN
Classifier: Programming Language :: Python :: 3
Classifier: License :: OSI Approved :: MIT License
Classifier: Operating System :: OS Independent
Requires-Python: >=3.6
Requires-Dist: opencv-python
Requires-Dist: flask
Requires-Dist: flask-basicauth
